cleora_saas_api/__init__.py
cleora_saas_api/api/__init__.py
cleora_saas_api/api/api.py
cleora_saas_api/api/api_endpoints_adresses.py
cleora_saas_api/api/dto_keys.py
cleora_saas_api/cli.py
cleora_saas_api/config.py
cleora_saas_api/download.py
cleora_saas_api/file_hash.py
cleora_saas_api/find_input_in_existing_runs.py
cleora_saas_api/find_string_index.py
cleora_saas_api/get_info.py
cleora_saas_api/input_details/__init__.py
cleora_saas_api/input_details/create_input_details.py
cleora_saas_api/input_details/generate_input_from_input_name.py
cleora_saas_api/input_details/generate_input_from_local.py
cleora_saas_api/input_details/generate_input_from_run_name.py
cleora_saas_api/input_details/generete_input_from_run_by_id.py
cleora_saas_api/input_details/input_file_details.py
cleora_saas_api/login/login_by_custom_token.py
cleora_saas_api/login/login_by_refresh_token.py
cleora_saas_api/retry_on_failure.py
cleora_saas_api/token/access_token.py
cleora_saas_api/token/remove_query_params.py
cleora_saas_api/token/token_managment.py
cleora_saas_api/token/token_model.py
cleora_saas_api/upload.py
cleora_saas_api-0.1.7.dist-info/METADATA
cleora_saas_api-0.1.7.dist-info/WHEEL
cleora_saas_api-0.1.7.dist-info/entry_points.txt
cleora_saas_api-0.1.7.dist-info/RECORD
